eBird2ABAP/__init__.py
eBird2ABAP/ebird2card.py
eBird2ABAP/matched_species.csv
eBird2ABAP/utils.py
eBird2ABAP-0.2.1.dist-info/METADATA
eBird2ABAP-0.2.1.dist-info/WHEEL
eBird2ABAP-0.2.1.dist-info/top_level.txt
eBird2ABAP-0.2.1.dist-info/RECORD
