Metadata-Version: 2.1
Name: eBird2ABAP
Version: 0.2.1
Summary: Create ABAP card from eBird data
Author: Raphaël Nussbaumer
Requires-Dist: numpy
Requires-Dist: pandas
